{
  "slot_id": "73548043f724464b",
  "page_path": "/blog/red-invitados-iot-segura-mexico.html",
  "normalized_page_path": "/blog/red-invitados-iot-segura-mexico.html",
  "slot_key": "inline-2",
  "slot_type": "inline",
  "market": "MX",
  "anchor_selector": "h2",
  "anchor_index": 1,
  "insertion_mode": "after",
  "priority_level": 3,
  "page_is_home": false,
  "risk_score": 0.2,
  "risk_factors": [
    "image_heavy"
  ],
  "anchor_text": "Que es una red de invitados y por que importa",
  "container_selector": "#contenido",
  "container_css_context": "html > body > main",
  "selected": false
}
